{
  "skill": "spectral_throw",
  "normalized_name": "spectral_throw",
  "source_url": "https://www.youtube.com/watch?v=FCyYPvXsskk",
  "source_type": "youtube_description_or_pinned_comment",
  "pob_url": "https://pobb.in/x27qgyntkBcA",
  "xml_path": "C:\\Users\\joao.carvalho\\Desktop\\Robô\\Agente - PoE_GDRIVE_STAGE\\data\\poe_ninja\\poe_ninja_dataset\\xml\\spectral_throw\\3_28_FCyYPvXsskk_9b38d972.xml",
  "patch": "3.28",
  "league": "3.28",
  "author": "Palsteron",
  "build_title": "Kinetic Fusillade Ballista Champion | Leaguestart Build Guide for 3.28 Mirage | Path of Exile",
  "collected_at": "2026-07-16T10:06:35Z",
  "status": "generated",
  "original_group_folder": "youtube"
}