{
  "skill": "flesh_and_stone",
  "normalized_name": "flesh_and_stone",
  "source_url": "https://www.youtube.com/watch?v=DfSB4HyHWHg",
  "source_type": "youtube_description_or_pinned_comment",
  "pob_url": "https://pobb.in/x5wbNJdRaazN",
  "xml_path": "C:\\Users\\joao.carvalho\\Desktop\\Robô\\Agente - PoE_GDRIVE_STAGE\\data\\poe_ninja\\poe_ninja_dataset\\xml\\flesh_and_stone\\3_28_DfSB4HyHWHg_057ddbc4.xml",
  "patch": "3.28",
  "league": "3.28",
  "author": "Alohaa",
  "build_title": "Endgame Slayer Static Strike Build | Clear All Content & Level to 100 | PoE 3.28",
  "collected_at": "2026-07-16T10:08:53Z",
  "status": "generated",
  "original_group_folder": "youtube"
}