<?xml version="1.0" encoding="UTF-8"?>
<PathOfBuilding>
	<Build level="95" targetVersion="3_0" pantheonMajorGod="Lunaris" bandit="Alira" className="Ranger" ascendClassName="Warden" characterLevelAutoMode="false" mainSocketGroup="2" viewMode="TREE" pantheonMinorGod="Ryslatha">
		<PlayerStat stat="AverageDamage" value="151586.3447366"/>
		<PlayerStat stat="AverageBurstDamage" value="151586.3447366"/>
		<PlayerStat stat="Speed" value="2.665"/>
		<PlayerStat stat="TotemPlacementTime" value="0.3125"/>
		<PlayerStat stat="PreEffectiveCritChance" value="100"/>
		<PlayerStat stat="CritChance" value="94"/>
		<PlayerStat stat="CritMultiplier" value="5.46"/>
		<PlayerStat stat="HitChance" value="94"/>
		<PlayerStat stat="TotalDPS" value="403977.60872303"/>
		<PlayerStat stat="TotalDot" value="0"/>
		<PlayerStat stat="WithBleedDPS" value="403977.60872303"/>
		<PlayerStat stat="IgniteDPS" value="4086.6940120411"/>
		<PlayerStat stat="WithIgniteDPS" value="408064.30273507"/>
		<PlayerStat stat="WithPoisonDPS" value="403977.60872303"/>
		<PlayerStat stat="TotalDotDPS" value="4086.6940120411"/>
		<PlayerStat stat="CullingDPS" value="45340.478081675"/>
		<PlayerStat stat="ReservationDPS" value="0"/>
		<PlayerStat stat="CombinedDPS" value="453404.78081675"/>
		<PlayerStat stat="ManaCost" value="28"/>
		<PlayerStat stat="ManaPercentCost" value="0"/>
		<PlayerStat stat="ManaPerSecondCost" value="89.6"/>
		<PlayerStat stat="ManaPercentPerSecondCost" value="0"/>
		<PlayerStat stat="LifeCost" value="0"/>
		<PlayerStat stat="LifePercentCost" value="0"/>
		<PlayerStat stat="LifePerSecondCost" value="0"/>
		<PlayerStat stat="LifePercentPerSecondCost" value="0"/>
		<PlayerStat stat="ESCost" value="0"/>
		<PlayerStat stat="ESPerSecondCost" value="0"/>
		<PlayerStat stat="ESPercentPerSecondCost" value="0"/>
		<PlayerStat stat="RageCost" value="0"/>
		<PlayerStat stat="SoulCost" value="0"/>
		<PlayerStat stat="Str" value="195"/>
		<PlayerStat stat="ReqStr" value="115"/>
		<PlayerStat stat="Dex" value="256"/>
		<PlayerStat stat="ReqDex" value="212"/>
		<PlayerStat stat="Int" value="131"/>
		<PlayerStat stat="ReqInt" value="120"/>
		<PlayerStat stat="Devotion" value="0"/>
		<PlayerStat stat="TotalEHP" value="14737.281581213"/>
		<PlayerStat stat="PhysicalMaximumHitTaken" value="3714"/>
		<PlayerStat stat="LightningMaximumHitTaken" value="12321"/>
		<PlayerStat stat="FireMaximumHitTaken" value="12321"/>
		<PlayerStat stat="ColdMaximumHitTaken" value="12778"/>
		<PlayerStat stat="ChaosMaximumHitTaken" value="3243"/>
		<PlayerStat stat="MainHandAccuracy" value="2924"/>
		<PlayerStat stat="Life" value="3243"/>
		<PlayerStat stat="Spec:LifeInc" value="69"/>
		<PlayerStat stat="LifeUnreserved" value="3243"/>
		<PlayerStat stat="LifeRecoverable" value="3243"/>
		<PlayerStat stat="LifeUnreservedPercent" value="100"/>
		<PlayerStat stat="LifeRegenRecovery" value="64.9"/>
		<PlayerStat stat="LifeLeechGainRate" value="0"/>
		<PlayerStat stat="Mana" value="924"/>
		<PlayerStat stat="Spec:ManaInc" value="28"/>
		<PlayerStat stat="ManaUnreserved" value="114"/>
		<PlayerStat stat="ManaUnreservedPercent" value="12.337662337662"/>
		<PlayerStat stat="ManaRegenRecovery" value="80.7"/>
		<PlayerStat stat="ManaLeechGainRate" value="0"/>
		<PlayerStat stat="EnergyShield" value="0"/>
		<PlayerStat stat="EnergyShieldRecoveryCap" value="0"/>
		<PlayerStat stat="Spec:EnergyShieldInc" value="0"/>
		<PlayerStat stat="EnergyShieldRegenRecovery" value="0"/>
		<PlayerStat stat="EnergyShieldLeechGainRate" value="0"/>
		<PlayerStat stat="Ward" value="0"/>
		<PlayerStat stat="Rage" value="0"/>
		<PlayerStat stat="RageRegenRecovery" value="0"/>
		<PlayerStat stat="Evasion" value="23769"/>
		<PlayerStat stat="Spec:EvasionInc" value="381"/>
		<PlayerStat stat="MeleeEvadeChance" value="74"/>
		<PlayerStat stat="ProjectileEvadeChance" value="74"/>
		<PlayerStat stat="Armour" value="2221"/>
		<PlayerStat stat="Spec:ArmourInc" value="0"/>
		<PlayerStat stat="PhysicalDamageReduction" value="18"/>
		<PlayerStat stat="EffectiveBlockChance" value="0"/>
		<PlayerStat stat="EffectiveSpellBlockChance" value="0"/>
		<PlayerStat stat="AttackDodgeChance" value="0"/>
		<PlayerStat stat="SpellDodgeChance" value="0"/>
		<PlayerStat stat="EffectiveSpellSuppressionChance" value="92.71"/>
		<PlayerStat stat="FireResist" value="75"/>
		<PlayerStat stat="FireResistOverCap" value="33"/>
		<PlayerStat stat="ColdResist" value="76"/>
		<PlayerStat stat="ColdResistOverCap" value="14"/>
		<PlayerStat stat="LightningResist" value="75"/>
		<PlayerStat stat="LightningResistOverCap" value="19"/>
		<PlayerStat stat="ChaosResist" value="0"/>
		<PlayerStat stat="ChaosResistOverCap" value="0"/>
		<PlayerStat stat="EffectiveMovementSpeedMod" value="2.3"/>
		<PlayerStat stat="FullDPS" value="0"/>
		<PlayerStat stat="FullDotDPS" value="0"/>
		<PlayerStat stat="PowerCharges" value="3"/>
		<PlayerStat stat="PowerChargesMax" value="3"/>
		<PlayerStat stat="FrenzyCharges" value="3"/>
		<PlayerStat stat="FrenzyChargesMax" value="3"/>
		<PlayerStat stat="EnduranceCharges" value="0"/>
		<PlayerStat stat="EnduranceChargesMax" value="3"/>
		<PlayerStat stat="ActiveTotemLimit" value="7"/>
		<TimelessData devotionVariant2="1" searchListFallback="" searchList="" devotionVariant1="1"/>
	</Build>
	<Import exportParty="false"/>
	<Party destination="All" ShowAdvanceTools="false" append="false"/>
	<Tree activeSpec="1">
		<Spec clusterHashFormatVersion="2" masteryEffects="{49391,64511},{48508,27718},{6427,56951},{31039,9986},{3571,12119},{44206,26997},{49820,45317},{56519,44252},{65528,57074}" ascendClassId="1" nodes="13375,32117,65829,65826,5237,65824,65817,49820,65834,2060,5926,34483,36221,34978,63251,66832,56295,36287,42178,14292,41119,37425,66841,66835,25260,22748,42632,27788,33753,53421,29662,18436,6910,65427,45593,32763,65528,35851,49900,64888,65502,39861,33989,65210,6797,64235,63139,22845,12794,63618,65830,53882,19858,48508,38149,46277,58650,31039,60942,6427,58427,32514,9206,61306,14804,50459,61834,49978,55750,18770,5408,22266,60180,59606,3571,53114,12412,40104,25178,59220,11489,56519,60735,31364,1461,8920,8938,62744,27444,39821,10840,23334,65808,52904,29454,49459,444,32555,20807,15290,47484,35086,47422,18182,44134,62721,45202,13935,55414,30455,54142,9469,49391,30679,9373,20953,6264,12948,61573,60592,24133,44206,27656,16848,12801,11497,21019" secondaryAscendClassId="0" treeVersion="3_28" classId="2">
			<URL>
				https://www.pathofexile.com/passive-skill-tree/AAAABgIBczQ_fXUUdcKcCAwXJoazjX2IovcT2-eNv6TCN9Sgn5IxYqxY3KaIbIyD2dCtc95IBBr-_5OyGX_7__iMC8Ls_Xj_3pu1hMX-uhqN-uv2o1k9Mfr4gtJ6TZK9fJUFtMXlGnk_7g4ZG38CI_bvejnU8YrDOtnGSVIVIFb66xTo1g3zz3owfJyoYlrnVCzh3MftP3qEBbUi2CLq9RhrNJuNKlhbJs6ocw7BMwG8fytRRzu6uXyJDrk-RwasZvUBsJI2b9h2dvfTfiT9wO931ySdUdkYeDKU8IXssF5FrK5sCEHQMgEs6VIbCgElASIBIAEZASoFEAUZBRMBJgEQCbEFwpze8v_4bEa9fCcCeT_edxkbL1cN86zc3Mf7_8DvaXWsrg==
			</URL>
			<Sockets>
				<Socket nodeId="61834" itemId="24"/>
				<Socket nodeId="33753" itemId="17"/>
				<Socket nodeId="18436" itemId="16"/>
				<Socket nodeId="32763" itemId="22"/>
				<Socket nodeId="34483" itemId="18"/>
				<Socket nodeId="33989" itemId="19"/>
				<Socket nodeId="60735" itemId="23"/>
				<Socket nodeId="22748" itemId="20"/>
				<Socket nodeId="6910" itemId="21"/>
			</Sockets>
			<Overrides>
				<Override dn="Tattoo of the Ramako Sniper" icon="Art/2DArt/SkillIcons/passives/projectilespeed.png" nodeId="22266" activeEffectImage="Art/2DArt/UIImages/InGame/AncestralTrial/PassiveTreeTattoos/RamakoTribePassiveBG.png">
					5% increased Projectile Speed
				</Override>
				<Override dn="Tattoo of the Ramako Sniper" icon="Art/2DArt/SkillIcons/passives/projectilespeed.png" nodeId="444" activeEffectImage="Art/2DArt/UIImages/InGame/AncestralTrial/PassiveTreeTattoos/RamakoTribePassiveBG.png">
					5% increased Projectile Speed
				</Override>
				<Override dn="Tattoo of the Ramako Sniper" icon="Art/2DArt/SkillIcons/passives/projectilespeed.png" nodeId="32555" activeEffectImage="Art/2DArt/UIImages/InGame/AncestralTrial/PassiveTreeTattoos/RamakoTribePassiveBG.png">
					5% increased Projectile Speed
				</Override>
				<Override dn="Tattoo of the Ramako Sniper" icon="Art/2DArt/SkillIcons/passives/projectilespeed.png" nodeId="5237" activeEffectImage="Art/2DArt/UIImages/InGame/AncestralTrial/PassiveTreeTattoos/RamakoTribePassiveBG.png">
					5% increased Projectile Speed
				</Override>
				<Override dn="Tattoo of the Tasalio Warrior" icon="Art/2DArt/SkillIcons/passives/AttackBlindNode.png" nodeId="52904" activeEffectImage="Art/2DArt/UIImages/InGame/AncestralTrial/PassiveTreeTattoos/TasalioTribePassiveBG.png">
					5% chance to Blind Enemies on Hit with Attacks
				</Override>
				<Override dn="Tattoo of the Ramako Sniper" icon="Art/2DArt/SkillIcons/passives/projectilespeed.png" nodeId="39861" activeEffectImage="Art/2DArt/UIImages/InGame/AncestralTrial/PassiveTreeTattoos/RamakoTribePassiveBG.png">
					5% increased Projectile Speed
				</Override>
				<Override dn="Tattoo of the Ramako Sniper" icon="Art/2DArt/SkillIcons/passives/projectilespeed.png" nodeId="59606" activeEffectImage="Art/2DArt/UIImages/InGame/AncestralTrial/PassiveTreeTattoos/RamakoTribePassiveBG.png">
					5% increased Projectile Speed
				</Override>
				<Override dn="Tattoo of the Ramako Sniper" icon="Art/2DArt/SkillIcons/passives/projectilespeed.png" nodeId="12412" activeEffectImage="Art/2DArt/UIImages/InGame/AncestralTrial/PassiveTreeTattoos/RamakoTribePassiveBG.png">
					5% increased Projectile Speed
				</Override>
				<Override dn="Tattoo of the Ramako Sniper" icon="Art/2DArt/SkillIcons/passives/projectilespeed.png" nodeId="36287" activeEffectImage="Art/2DArt/UIImages/InGame/AncestralTrial/PassiveTreeTattoos/RamakoTribePassiveBG.png">
					5% increased Projectile Speed
				</Override>
				<Override dn="Tattoo of the Ramako Sniper" icon="Art/2DArt/SkillIcons/passives/projectilespeed.png" nodeId="30679" activeEffectImage="Art/2DArt/UIImages/InGame/AncestralTrial/PassiveTreeTattoos/RamakoTribePassiveBG.png">
					5% increased Projectile Speed
				</Override>
				<Override dn="Tattoo of the Ramako Sniper" icon="Art/2DArt/SkillIcons/passives/projectilespeed.png" nodeId="14292" activeEffectImage="Art/2DArt/UIImages/InGame/AncestralTrial/PassiveTreeTattoos/RamakoTribePassiveBG.png">
					5% increased Projectile Speed
				</Override>
				<Override dn="Tattoo of the Ramako Sniper" icon="Art/2DArt/SkillIcons/passives/projectilespeed.png" nodeId="46277" activeEffectImage="Art/2DArt/UIImages/InGame/AncestralTrial/PassiveTreeTattoos/RamakoTribePassiveBG.png">
					5% increased Projectile Speed
				</Override>
				<Override dn="Tattoo of the Ramako Sniper" icon="Art/2DArt/SkillIcons/passives/projectilespeed.png" nodeId="60942" activeEffectImage="Art/2DArt/UIImages/InGame/AncestralTrial/PassiveTreeTattoos/RamakoTribePassiveBG.png">
					5% increased Projectile Speed
				</Override>
				<Override dn="Tattoo of the Ramako Sniper" icon="Art/2DArt/SkillIcons/passives/projectilespeed.png" nodeId="20807" activeEffectImage="Art/2DArt/UIImages/InGame/AncestralTrial/PassiveTreeTattoos/RamakoTribePassiveBG.png">
					5% increased Projectile Speed
				</Override>
				<Override dn="Tattoo of the Ramako Sniper" icon="Art/2DArt/SkillIcons/passives/projectilespeed.png" nodeId="49978" activeEffectImage="Art/2DArt/UIImages/InGame/AncestralTrial/PassiveTreeTattoos/RamakoTribePassiveBG.png">
					5% increased Projectile Speed
				</Override>
				<Override dn="Tattoo of the Ramako Sniper" icon="Art/2DArt/SkillIcons/passives/projectilespeed.png" nodeId="8938" activeEffectImage="Art/2DArt/UIImages/InGame/AncestralTrial/PassiveTreeTattoos/RamakoTribePassiveBG.png">
					5% increased Projectile Speed
				</Override>
				<Override dn="Tattoo of the Ramako Sniper" icon="Art/2DArt/SkillIcons/passives/projectilespeed.png" nodeId="61306" activeEffectImage="Art/2DArt/UIImages/InGame/AncestralTrial/PassiveTreeTattoos/RamakoTribePassiveBG.png">
					5% increased Projectile Speed
				</Override>
				<Override dn="Tattoo of the Ramako Sniper" icon="Art/2DArt/SkillIcons/passives/projectilespeed.png" nodeId="1461" activeEffectImage="Art/2DArt/UIImages/InGame/AncestralTrial/PassiveTreeTattoos/RamakoTribePassiveBG.png">
					5% increased Projectile Speed
				</Override>
				<Override dn="Tattoo of the Ramako Sniper" icon="Art/2DArt/SkillIcons/passives/projectilespeed.png" nodeId="49900" activeEffectImage="Art/2DArt/UIImages/InGame/AncestralTrial/PassiveTreeTattoos/RamakoTribePassiveBG.png">
					5% increased Projectile Speed
				</Override>
			</Overrides>
		</Spec>
	</Tree>
	<Notes>
		
	</Notes>
	<Skills sortGemsByDPSField="CombinedDPS" activeSkillSet="1" sortGemsByDPS="true" defaultGemQuality="0" defaultGemLevel="normalMaximum" showSupportGemTypes="ALL" showLegacyGems="false">
		<SkillSet id="1">
			<Skill slot="Boots" mainActiveSkill="1" includeInFullDPS="nil" mainActiveSkillCalcs="1" enabled="true">
				<Gem enableGlobal2="true" level="1" enableGlobal1="true" variantId="FlameDash" skillId="FlameDash" quality="20" gemId="Metadata/Items/Gems/SkillGemFlameDash" enabled="true" count="1" nameSpec="Flame Dash"/>
				<Gem enableGlobal2="true" level="20" enableGlobal1="true" variantId="Automation" skillId="Automation" quality="20" gemId="Metadata/Items/Gems/SkillGemAutomation" enabled="true" count="1" nameSpec="Automation"/>
				<Gem enableGlobal2="true" level="20" enableGlobal1="true" variantId="SupportMoreDuration" skillId="SupportMoreDuration" quality="20" gemId="Metadata/Items/Gems/SupportGemIncreasedDuration" enabled="true" count="1" nameSpec="More Duration"/>
				<Gem enableGlobal2="true" level="19" enableGlobal1="true" variantId="QuickGuard" skillId="QuickGuard" quality="20" gemId="Metadata/Items/Gems/SkillGemSteelskin" enabled="false" count="1" nameSpec="Steelskin"/>
			</Skill>
			<Skill slot="Body Armour" mainActiveSkill="1" includeInFullDPS="nil" mainActiveSkillCalcs="1" enabled="true" imbuedSupport="Increased Critical Damage">
				<Gem enableGlobal2="true" level="20" enableGlobal1="true" variantId="SupportVolatility" skillId="SupportVolatility" quality="20" gemId="Metadata/Items/Gems/SupportGemVolatility" enabled="true" count="1" nameSpec="Volatility"/>
				<Gem enableGlobal2="true" level="20" enableGlobal1="true" variantId="SupportHypothermia" skillId="SupportHypothermia" quality="20" gemId="Metadata/Items/Gems/SupportGemDamageAgainstChilled" enabled="true" count="1" nameSpec="Hypothermia"/>
				<Gem enableGlobal2="true" level="20" enableGlobal1="true" variantId="ArtilleryBallistaAltX" skillId="ArtilleryBallistaAltX" quality="20" gemId="Metadata/Items/Gems/SkillGemArtilleryBallista" enabled="true" count="1" nameSpec="Artillery Ballista of Cross Strafe"/>
				<Gem enableGlobal2="true" level="21" enableGlobal1="true" variantId="SupportAddedLightningDamage" skillId="SupportAddedLightningDamage" quality="20" gemId="Metadata/Items/Gems/SupportGemAddedLightningDamage" enabled="true" count="1" nameSpec="Added Lightning Damage"/>
				<Gem enableGlobal2="true" level="20" enableGlobal1="true" variantId="SupportIncreasedAreaofEffect" skillId="SupportIncreasedAreaOfEffect" quality="20" gemId="Metadata/Items/Gems/SupportGemIncreasedAreaOfEffect" enabled="true" count="1" nameSpec="Increased Area of Effect"/>
				<Gem enableGlobal2="true" level="3" enableGlobal1="true" variantId="SupportInvertTheRules" skillId="SupportInvertTheRules" quality="20" gemId="Metadata/Items/Gems/SupportGemInvertTheRules" enabled="true" count="1" nameSpec="Invert the Rules"/>
			</Skill>
			<Skill slot="Helmet" mainActiveSkill="1" includeInFullDPS="nil" mainActiveSkillCalcs="1" enabled="true">
				<Gem enableGlobal2="true" level="20" enableGlobal1="true" variantId="SupportPowerChargeOnCritical" skillId="SupportPowerChargeOnCritical" quality="0" gemId="Metadata/Items/Gems/SupportGemPowerChargeOnCrit" enabled="true" count="1" nameSpec="Power Charge On Critical"/>
				<Gem enableGlobal2="true" level="20" enableGlobal1="true" variantId="EnsnaringArrow" skillId="EnsnaringArrow" quality="20" gemId="Metadata/Items/Gems/SkillGemEnsnaringArrow" enabled="true" count="1" nameSpec="Ensnaring Arrow"/>
				<Gem enableGlobal2="true" level="20" enableGlobal1="true" variantId="Frenzy" skillId="Frenzy" quality="20" gemId="Metadata/Items/Gems/SkillGemFrenzy" enabled="true" count="1" nameSpec="Frenzy"/>
				<Gem enableGlobal2="true" level="20" enableGlobal1="true" variantId="SupportManaforgedArrows" skillId="SupportManaforgedArrows" quality="20" gemId="Metadata/Items/Gems/SupportGemManaforgedArrows" enabled="true" count="1" nameSpec="Manaforged Arrows"/>
			</Skill>
			<Skill slot="Weapon 1" mainActiveSkill="1" includeInFullDPS="nil" mainActiveSkillCalcs="1" enabled="true">
				<Gem enableGlobal2="true" level="20" enableGlobal1="true" variantId="SupportLessDuration" skillId="SupportLessDuration" quality="23" gemId="Metadata/Items/Gems/SupportGemReducedDuration" enabled="true" count="1" nameSpec="Less Duration"/>
				<Gem enableGlobal2="true" level="20" enableGlobal1="true" variantId="SupportLifeGainOnHit" skillId="SupportLifeGainOnHit" quality="20" gemId="Metadata/Items/Gems/SupportGemLifeGainOnHit" enabled="true" count="1" nameSpec="Life Gain on Hit"/>
				<Gem enableGlobal2="true" level="1" enableGlobal1="true" variantId="SupportHextouch" skillId="SupportHextouch" quality="0" gemId="Metadata/Items/Gems/SupportGemCurseOnHit" enabled="true" count="1" nameSpec="Hextouch"/>
				<Gem enableGlobal2="true" level="1" enableGlobal1="true" variantId="TemporalChains" skillId="TemporalChains" quality="0" gemId="Metadata/Items/Gems/SkillGemTemporalChains" enabled="true" count="1" nameSpec="Temporal Chains"/>
				<Gem enableGlobal2="true" level="2" enableGlobal1="true" variantId="RainOfArrowsAltY" skillId="RainOfArrowsAltY" quality="20" gemId="Metadata/Items/Gems/SkillGemRainOfArrows" enabled="true" count="1" nameSpec="Rain of Arrows of Saturation"/>
				<Gem enableGlobal2="true" level="20" enableGlobal1="true" variantId="SupportManaforgedArrows" skillId="SupportManaforgedArrows" quality="20" gemId="Metadata/Items/Gems/SupportGemManaforgedArrows" enabled="true" count="1" nameSpec="Manaforged Arrows"/>
			</Skill>
			<Skill slot="Gloves" mainActiveSkill="1" includeInFullDPS="nil" mainActiveSkillCalcs="1" enabled="true">
				<Gem enableGlobal2="true" level="3" enableGlobal1="true" variantId="SupportEnlighten" skillId="SupportEnlighten" quality="20" gemId="Metadata/Items/Gems/SupportGemAdditionalXP" enabled="true" count="1" nameSpec="Enlighten"/>
				<Gem enableGlobal2="true" level="20" enableGlobal1="true" variantId="Clarity" skillId="Clarity" quality="0" gemId="Metadata/Items/Gems/SkillGemClarity" enabled="true" count="1" nameSpec="Clarity"/>
				<Gem enableGlobal2="true" level="20" enableGlobal1="true" variantId="PurityOfElements" skillId="PurityOfElements" quality="20" gemId="Metadata/Items/Gems/SkillGemPurity" enabled="true" count="1" nameSpec="Purity of Elements"/>
			</Skill>
			<Skill slot="Amulet" mainActiveSkill="nil" includeInFullDPS="nil" label="" mainActiveSkillCalcs="nil" enabled="true" source="Item:10:Hyrri&apos;s Truth, Jade Amulet">
				<Gem enableGlobal2="nil" level="30" enableGlobal1="true" skillId="Precision" quality="0" enabled="true" count="nil" nameSpec="Precision"/>
			</Skill>
		</SkillSet>
	</Skills>
	<Calcs>
		<Input name="misc_buffMode" string="EFFECTIVE"/>
		<Input name="skill_number" number="2"/>
		<Section subsection="ViewSkillDetails" collapsed="false" id="SkillSelect"/>
		<Section subsection="SkillHitDamage" collapsed="false" id="HitDamage"/>
		<Section subsection="ExertingWarcries" collapsed="false" id="Warcries"/>
		<Section subsection="SkillDamageoverTime" collapsed="false" id="Dot"/>
		<Section subsection="AttackCastRate" collapsed="false" id="Speed"/>
		<Section subsection="Crits" collapsed="false" id="Crit"/>
		<Section subsection="Impale" collapsed="false" id="Impale"/>
		<Section subsection="SkilltypespecificStats" collapsed="false" id="SkillTypeStats"/>
		<Section subsection="Accuracy" collapsed="false" id="HitChance"/>
		<Section subsection="Bleed" collapsed="false" id="Bleed"/>
		<Section subsection="Poison" collapsed="false" id="Poison"/>
		<Section subsection="Ignite" collapsed="false" id="Ignite"/>
		<Section subsection="Decay" collapsed="false" id="Decay"/>
		<Section subsection="LeechGainonHit" collapsed="false" id="LeechGain"/>
		<Section subsection="NonDamagingAilments" collapsed="false" id="EleAilments"/>
		<Section subsection="OtherEffects" collapsed="false" id="MiscEffects"/>
		<Section subsection="Attributes" collapsed="false" id="Attributes"/>
		<Section subsection="Life" collapsed="false" id="Life"/>
		<Section subsection="Mana" collapsed="false" id="Mana"/>
		<Section subsection="EnergyShield" collapsed="false" id="EnergyShield"/>
		<Section subsection="Ward" collapsed="false" id="Ward"/>
		<Section subsection="Resists" collapsed="false" id="Resist"/>
		<Section subsection="Armour" collapsed="false" id="Armour"/>
		<Section subsection="Evasion" collapsed="false" id="Evasion"/>
		<Section subsection="DamageAvoidance" collapsed="false" id="DamageAvoidance"/>
		<Section subsection="Block" collapsed="false" id="DamageAvoidance"/>
		<Section subsection="Dodge" collapsed="false" id="DamageAvoidance"/>
		<Section subsection="SpellSuppression" collapsed="false" id="DamageAvoidance"/>
		<Section subsection="Flasks" collapsed="false" id="Flasks"/>
		<Section subsection="UtilityFlasks" collapsed="true" id="Flasks"/>
		<Section subsection="LifeFlasks" collapsed="true" id="Flasks"/>
		<Section subsection="ManaFlasks" collapsed="true" id="Flasks"/>
		<Section subsection="Tinctures" collapsed="true" id="Flasks"/>
		<Section subsection="Rage" collapsed="true" id="Rage"/>
		<Section subsection="Charges" collapsed="true" id="Charges"/>
		<Section subsection="Endurance" collapsed="true" id="Charges"/>
		<Section subsection="Frenzy" collapsed="true" id="Charges"/>
		<Section subsection="Power" collapsed="true" id="Charges"/>
		<Section subsection="OtherDefences" collapsed="false" id="MiscDefences"/>
		<Section subsection="Fortification" collapsed="false" id="MiscDefences"/>
		<Section subsection="StunDuration" collapsed="false" id="MiscDefences"/>
		<Section subsection="OtherAvoidance" collapsed="true" id="MiscDefences"/>
		<Section subsection="OtherAilmentDefences" collapsed="true" id="MiscDefences"/>
		<Section subsection="DamageTaken" collapsed="false" id="DamageTaken"/>
		<Section subsection="DamagingHits" collapsed="false" id="DamageTaken"/>
		<Section subsection="EffectiveHealthPool" collapsed="false" id="DamageTaken"/>
		<Section subsection="MaximumHitTaken" collapsed="false" id="DamageTaken"/>
		<Section subsection="RecoupandHitTakenOverTime" collapsed="true" id="DamageTaken"/>
		<Section subsection="DotsandBuildDegens" collapsed="false" id="DamageTaken"/>
		<Section subsection="EnemyDegens" collapsed="true" id="DamageTaken"/>
	</Calcs>
	<TreeView searchStr="" zoomY="0" zoomLevel="3" showStatDifferences="true" zoomX="0"/>
	<Items activeItemSet="1" showStatDifferences="true" useSecondWeaponSet="false">
		<Item id="1">
			Rarity: RARE
Eagle Spark
Slink Boots
Evasion: 323
EvasionBasePercentile: 0.6261
Unique ID: e7839a6abf0885fe58e245c8f830a950bddf378eecff31330433cf22154566ce
Redeemer Item
Item Level: 85
Quality: 20
Sockets: B-B-R-R
LevelReq: 70
Implicits: 0
+14% chance to Suppress Spell Damage
+124 to maximum Life
+48% to Fire Resistance
+10% to Cold Resistance
25% increased Movement Speed
6% chance to gain Elusive on Critical Strike
			<ModRange range="0.5" id="1"/>
			<ModRange range="0.5" id="2"/>
			<ModRange range="0.5" id="3"/>
			<ModRange range="0.5" id="4"/>
			<ModRange range="0.5" id="5"/>
			<ModRange range="0.5" id="6"/>
		</Item>
		<Item id="2">
			Rarity: RARE
Oblivion Rod
Artillery Quiver
Unique ID: 662607c93bd5d995637c704d7149344c25752530069ed3cf7579a4a4430e60a8
Item Level: 83
Quality: 0
LevelReq: 74
Implicits: 1
30% increased Totem Placement speed
Adds 38 to 82 Fire Damage to Attacks
+31% to Critical Strike Multiplier with Bows
+107 to maximum Life
+28% to Lightning Resistance
Bow Attacks fire an additional Arrow
{crafted}Adds 4 to 69 Lightning Damage to Attacks
			<ModRange range="0.5" id="1"/>
			<ModRange range="0.5" id="2"/>
			<ModRange range="0.5" id="3"/>
			<ModRange range="0.5" id="4"/>
			<ModRange range="0.5" id="5"/>
			<ModRange range="0.5" id="6"/>
			<ModRange range="0.5" id="7"/>
		</Item>
		<Item id="3">
			Rarity: UNIQUE
Daresso&apos;s Defiance
Full Dragonscale
Armour: 1862
ArmourBasePercentile: 0.9276
Evasion: 1477
EvasionBasePercentile: 0.9297
Unique ID: fdaf7aff6e8631d4de1da7e9e0dcba344dc59b617d57a207999a407e47234167
Item Level: 73
Quality: 19
Sockets: R-G-G-B-B-B
LevelReq: 63
Implicits: 1
+2 to Level of Socketed AoE Gems
192% increased Armour and Evasion
+72 to maximum Life
2% of Attack Damage Leeched as Life
You lose all Endurance Charges when Hit
You gain an Endurance Charge on Kill
You gain Onslaught for 5 seconds per Endurance Charge when Hit
100% increased Effect of Onslaught on you
Corrupted
			<ModRange range="0.5" id="1"/>
			<ModRange range="0.5" id="2"/>
			<ModRange range="0.5" id="3"/>
			<ModRange range="0.5" id="4"/>
			<ModRange range="0.5" id="6"/>
			<ModRange range="0.5" id="7"/>
			<ModRange range="0.5" id="8"/>
		</Item>
		<Item id="4">
			Rarity: UNIQUE
Replica Heatshiver
Leather Hood
Evasion: 261
EvasionBasePercentile: 0.7371
Unique ID: 8ab622a591c1147ff168f022e2f7c201900086889710b0bc2bf2852114453d10
Item Level: 86
Quality: 20
Sockets: B-G-G-G
LevelReq: 20
Implicits: 1
Cannot be Blinded
81% increased Evasion Rating
60% increased Mana Regeneration Rate
+30% to Cold Resistance
+20% to Lightning Resistance
Gain 1% of Lightning Damage as Extra Cold Damage per 2% Shock Effect on Enemy
Corrupted
			<ModRange range="0.5" id="1"/>
			<ModRange range="0.5" id="2"/>
			<ModRange range="0.5" id="3"/>
			<ModRange range="0.5" id="4"/>
			<ModRange range="0.5" id="5"/>
			<ModRange range="0.5" id="6"/>
		</Item>
		<Item id="5">
			Rarity: RARE
Rapture Eye
Gold Ring
Unique ID: 88a75c02f42351a318e6246727e6e5094e365beec68d8124ae2aca210c4eec2a
Item Level: 85
LevelReq: 64
Implicits: 1
15% increased Rarity of Items found
+37 to Strength
+108 to maximum Life
+53 to maximum Mana
+44% to Cold Resistance
+40% to Lightning Resistance
{crafted}Non-Channelling Skills have -7 to Total Mana Cost
			<ModRange range="0.5" id="1"/>
			<ModRange range="0.5" id="2"/>
			<ModRange range="0.5" id="3"/>
			<ModRange range="0.5" id="4"/>
			<ModRange range="0.5" id="5"/>
			<ModRange range="0.5" id="6"/>
			<ModRange range="0.5" id="7"/>
		</Item>
		<Item id="6">
			Rarity: UNIQUE
Coiling Whisper
Amethyst Ring
Unique ID: e56bd2653be29d10e694754395b75d1a4f4dcccaee642a3c294005d9aac4e55a
Item Level: 87
LevelReq: 30
Implicits: 1
+23% to Chaos Resistance
30% reduced Area of Effect of Hex Skills
Targets are Unaffected by your Hexes
When 90% of your Hex&apos;s Duration Expires on an Enemy, Eat 1 Soul per Enemy Power
			<ModRange range="0.5" id="1"/>
			<ModRange range="0.5" id="2"/>
			<ModRange range="0.5" id="3"/>
			<ModRange range="0.5" id="4"/>
		</Item>
		<Item id="7">
			Rarity: RARE
Onslaught Branch
Spine Bow
Unique ID: b7d5ae2e3f1036717620931b0dadef6462b3da2e3d9b72681e8efc4881090e82
Item Level: 85
Quality: 20
Sockets: R-R-B-G-G-G
LevelReq: 70
Implicits: 2
{crafted}Quality does not increase Physical Damage
{crafted}1% increased Attack Speed per 8% Quality
{fractured}Adds 37 to 607 Lightning Damage
+27 to Dexterity and Intelligence
Adds 202 to 382 Fire Damage
Adds 152 to 289 Cold Damage
15% increased Attack Speed
Gain 10 Life per Enemy Killed
{crafted}27% increased Critical Strike Chance
			<ModRange range="0.5" id="1"/>
			<ModRange range="0.5" id="2"/>
			<ModRange range="0.5" id="3"/>
			<ModRange range="0.5" id="4"/>
			<ModRange range="0.5" id="5"/>
			<ModRange range="0.5" id="6"/>
			<ModRange range="0.5" id="7"/>
			<ModRange range="0.5" id="8"/>
			<ModRange range="0.5" id="9"/>
		</Item>
		<Item id="8">
			Rarity: RARE
Ghoul Hand
Wyvernscale Gauntlets
Armour: 269
ArmourBasePercentile: 0.6183
Evasion: 269
EvasionBasePercentile: 0.6183
Unique ID: 25f5978aa297acae2225c522542929155231e5e626fb464ee77953f2513a2ecb
Item Level: 85
Quality: 20
Sockets: B-B-B-G
LevelReq: 84
Implicits: 2
+5% chance to Suppress Spell Damage
Gain 1 Rage on Attack Hit
+48 to Strength
Adds 9 to 16 Cold Damage to Attacks
+124 to maximum Life
+48% to Fire Resistance
+24% to Chaos Resistance
{crafted}12% increased Area of Effect
{crafted}16% increased Area Damage
			<ModRange range="0.5" id="1"/>
			<ModRange range="0.5" id="2"/>
			<ModRange range="0.5" id="3"/>
			<ModRange range="0.5" id="4"/>
			<ModRange range="0.5" id="5"/>
			<ModRange range="0.5" id="6"/>
			<ModRange range="0.5" id="7"/>
			<ModRange range="0.5" id="8"/>
			<ModRange range="0.5" id="9"/>
		</Item>
		<Item id="9">
			Rarity: UNIQUE
Headhunter
Leather Belt
Unique ID: 68b571e9aef82588a156bc132a625db883575571c242796624d1bcf90d115208
Item Level: 80
LevelReq: 8
Implicits: 1
+39 to maximum Life
+66 to Strength
+51 to Dexterity
+56 to maximum Life
26% increased Damage with Hits against Rare monsters
When you Kill a Rare monster, you gain its Modifiers for 60 seconds
			<ModRange range="0.5" id="1"/>
			<ModRange range="0.5" id="2"/>
			<ModRange range="0.5" id="3"/>
			<ModRange range="0.5" id="4"/>
			<ModRange range="0.5" id="5"/>
		</Item>
		<Item id="10">
			Rarity: UNIQUE
Hyrri&apos;s Truth
Jade Amulet
Unique ID: 8d72ab5f872f4f5997d34fbf327ad53169e7e90878bc11892efa6ef2a78014d8
Item Level: 83
LevelReq: 5
Implicits: 2
{crafted}Allocates Surveillance
+28 to Dexterity
Grants Level 30 Precision Skill
+78 to Dexterity
+57% to Global Critical Strike Multiplier
Bow Attacks have Culling Strike
Precision has 100% increased Mana Reservation Efficiency
			<ModRange range="0.5" id="1"/>
			<ModRange range="0.5" id="2"/>
			<ModRange range="0.5" id="3"/>
			<ModRange range="0.5" id="4"/>
			<ModRange range="0.5" id="5"/>
			<ModRange range="0.5" id="6"/>
			<ModRange range="0.5" id="7"/>
		</Item>
		<Item id="11">
			Rarity: MAGIC
Enriched Rosethorn Tincture of Overpowering
Unique ID: 439776283ebcf99419e14aff3724aaf96a3ae3139d62cf5d58835673b3f706e6
Item Level: 85
Quality: 20
LevelReq: 68
Implicits: 1
239% increased Critical Strike Chance with Melee Weapons
35% increased effect
61% increased Mana Burn rate
Melee Weapon Damage Penetrates 29% Elemental Resistances
			<ModRange range="0.5" id="1"/>
			<ModRange range="0.5" id="2"/>
			<ModRange range="0.5" id="3"/>
			<ModRange range="0.5" id="4"/>
		</Item>
		<Item id="12">
			Rarity: MAGIC
Potent Prismatic Tincture of Mastery
Unique ID: 69e1d6d2ea57ff3d88a2817eb12005fae00bb8b29579cbeb36656b0f10562a18
Item Level: 85
Quality: 20
LevelReq: 68
Implicits: 1
160% increased Elemental Damage with Melee Weapons
35% increased effect
81% increased Mana Burn rate
45% increased Melee Weapon Attack Speed
			<ModRange range="0.5" id="1"/>
			<ModRange range="0.5" id="2"/>
			<ModRange range="0.5" id="3"/>
			<ModRange range="0.5" id="4"/>
		</Item>
		<Item id="13">
			Rarity: MAGIC
Doctor&apos;s Jade Flask of the Cheetah
Unique ID: 4ad8dfa76f1178fdc93735f8c486fa8a94caa7326c4257c1c9778d457ad735a9
Item Level: 85
Quality: 20
LevelReq: 68
Implicits: 0
22% chance to gain a Flask Charge when you deal a Critical Strike
14% increased Movement Speed during Effect
			<ModRange range="0.5" id="2"/>
			<ModRange range="0.5" id="3"/>
		</Item>
		<Item id="14">
			Rarity: MAGIC
Specialist&apos;s Quicksilver Flask of the Ibex
Unique ID: 8c320ee6919ecd431f8323cb6771f86c67b9ad610c36b3ea3acada0a64b1c7fb
Item Level: 69
Quality: 20
LevelReq: 49
Implicits: 1
{crafted}Used when Charges reach full
29% chance to gain a Flask Charge when you deal a Critical Strike
55% increased Evasion Rating during Effect
			<ModRange range="0.5" id="3"/>
			<ModRange range="0.5" id="4"/>
		</Item>
		<Item id="15">
			Rarity: MAGIC
Specialist&apos;s Divine Life Flask of Alleviation
Unique ID: 7785adb6b2324599aeccf6c1f596015df8e529ee2052c1fd869ec10d5b927e87
Item Level: 71
Quality: 20
LevelReq: 60
Implicits: 0
30% chance to gain a Flask Charge when you deal a Critical Strike
Grants Immunity to Bleeding for 10 seconds if used while Bleeding
Grants Immunity to Corrupted Blood for 10 seconds if used while affected by Corrupted Blood
			<ModRange range="0.5" id="1"/>
			<ModRange range="0.5" id="2"/>
			<ModRange range="0.5" id="3"/>
		</Item>
		<Item id="16">
			Rarity: UNIQUE
Forbidden Flesh
Cobalt Jewel
Unique ID: 96e1b20d63d7bbdad69eb92363d25b6a4f3d07bdd1a8bb76a48856e15b802774
Item Level: 86
Requires Class Ranger
Implicits: 0
Allocates Seasoned Hunter if you have the matching modifier on Forbidden Flame
Corrupted
			<ModRange range="0.5" id="1"/>
		</Item>
		<Item id="17">
			Rarity: RARE
Viper Shine
Medium Cluster Jewel
Unique ID: c9c25b0138a98fffded801d376e202f6a623a29ecf885398d8cfefa5110b1908
Item Level: 83
LevelReq: 54
Implicits: 3
{crafted}Adds 4 Passive Skills
{crafted}1 Added Passive Skill is a Jewel Socket
{crafted}Added Small Passive Skills grant: 12% increased Totem Damage
Added Small Passive Skills also grant: +3% to Fire Resistance
Added Small Passive Skills also grant: 4% increased Mana Regeneration Rate
1 Added Passive Skill is Ancestral Echo
1 Added Passive Skill is Sleepless Sentries
			<ModRange range="0.5" id="1"/>
			<ModRange range="0.5" id="2"/>
			<ModRange range="0.5" id="3"/>
			<ModRange range="0.5" id="4"/>
			<ModRange range="0.5" id="5"/>
			<ModRange range="0.5" id="6"/>
			<ModRange range="0.5" id="7"/>
		</Item>
		<Item id="18">
			Rarity: UNIQUE
Unnatural Instinct
Viridian Jewel
Unique ID: 92e46a99ecc5a7dc792ab28449556a7e5da0c5b447fa2b19b4603ec6d0782a18
Item Level: 84
Radius: Small
Implicits: 1
7% increased Effect of Non-Damaging Ailments
Allocated Small Passive Skills in Radius grant nothing
Grants all bonuses of Unallocated Small Passive Skills in Radius
Corrupted
			<ModRange range="0.5" id="1"/>
			<ModRange range="0.5" id="2"/>
			<ModRange range="0.5" id="3"/>
		</Item>
		<Item id="19">
			Rarity: UNIQUE
Rain of Splinters
Crimson Jewel
Unique ID: 317d84c6ebde3c21cd28a48e02269ec4e211b8c3b8b63c6a526e47520e3cb78c
Item Level: 83
Implicits: 0
37% reduced Totem Damage
Totems fire 2 additional Projectiles
Corrupted
			<ModRange range="0.5" id="1"/>
			<ModRange range="0.5" id="2"/>
		</Item>
		<Item id="20">
			Rarity: UNIQUE
Forbidden Flame
Crimson Jewel
Unique ID: 27c25a24f57052f4b379c22a006425b410c1048798a4993df21068d5d3d61454
Item Level: 87
Requires Class Ranger
Implicits: 0
Allocates Seasoned Hunter if you have the matching modifier on Forbidden Flesh
Corrupted
			<ModRange range="0.5" id="1"/>
		</Item>
		<Item id="21">
			Rarity: RARE
Oblivion Spark
Medium Cluster Jewel
Unique ID: 01312b2c475e1973cc82089c85c491de3c3bcb28c54c12b919a37d0475772416
Item Level: 71
LevelReq: 54
Implicits: 3
{crafted}Adds 4 Passive Skills
{crafted}1 Added Passive Skill is a Jewel Socket
{crafted}Added Small Passive Skills grant: 10% increased Effect of Non-Damaging Ailments
Added Small Passive Skills also grant: +4% to Chaos Resistance
Added Small Passive Skills also grant: +3% to Fire Resistance
1 Added Passive Skill is Blast-Freeze
1 Added Passive Skill is Eye of the Storm
			<ModRange range="0.5" id="1"/>
			<ModRange range="0.5" id="2"/>
			<ModRange range="0.5" id="3"/>
			<ModRange range="0.5" id="4"/>
			<ModRange range="0.5" id="5"/>
			<ModRange range="0.5" id="6"/>
			<ModRange range="0.5" id="7"/>
		</Item>
		<Item id="22">
			Rarity: RARE
Eagle Sliver
Large Cluster Jewel
Unique ID: efa8b068e5741458f109ef3900e2f35cf9494e6248ddeca17235b0c3b8122953
Item Level: 83
LevelReq: 54
Implicits: 3
{crafted}Adds 8 Passive Skills
{crafted}2 Added Passive Skills are Jewel Sockets
{crafted}Added Small Passive Skills grant: 12% increased Damage with Bows
Added Small Passive Skills grant: 12% increased Damage Over Time with Bow Skills
Added Small Passive Skills also grant: +30 to Armour
Added Small Passive Skills also grant: +3% to Chaos Resistance
1 Added Passive Skill is Broadside
1 Added Passive Skill is Smite the Weak
			<ModRange range="0.5" id="1"/>
			<ModRange range="0.5" id="2"/>
			<ModRange range="0.5" id="3"/>
			<ModRange range="0.5" id="4"/>
			<ModRange range="0.5" id="5"/>
			<ModRange range="0.5" id="6"/>
			<ModRange range="0.5" id="7"/>
		</Item>
		<Item id="23">
			Rarity: UNIQUE
The Light of Meaning
Prismatic Jewel
Unique ID: 8008c30eba9a9736b3786f5fe4851fee04efa9c18d573fa49321c68ebfa95864
Item Level: 85
Radius: Large
Implicits: 1
Corrupted Blood cannot be inflicted on you
Passive Skills in Radius also grant 7% increased Evasion Rating
Corrupted
			<ModRange range="0.5" id="1"/>
			<ModRange range="0.5" id="2"/>
		</Item>
		<Item id="24">
			Rarity: UNIQUE
Lioneye&apos;s Fall
Viridian Jewel
Unique ID: 3031e0940640a35f5907dcc83408b1d78e56f652529e1254cef36036da28752b
Item Level: 83
Radius: Medium
Implicits: 1
5% increased Area of Effect
Melee and Melee Weapon Type modifiers in Radius are Transformed to Bow Modifiers
Corrupted
			<ModRange range="0.5" id="1"/>
			<ModRange range="0.5" id="2"/>
		</Item>
		<ItemSet useSecondWeaponSet="false" id="1">
			<Slot itemPbURL="" name="Weapon 1" itemId="7"/>
			<Slot itemPbURL="" name="Ring 3" itemId="0"/>
			<Slot itemPbURL="" name="Belt Abyssal Socket 2" itemId="0"/>
			<Slot itemPbURL="" name="Weapon 1 Abyssal Socket 5" itemId="0"/>
			<Slot itemPbURL="" name="Weapon 2 Abyssal Socket 5" itemId="0"/>
			<Slot itemPbURL="" name="Weapon 1 Swap Abyssal Socket 6" itemId="0"/>
			<Slot itemPbURL="" name="Weapon 1 Abyssal Socket 6" itemId="0"/>
			<Slot itemPbURL="" name="Weapon 2 Abyssal Socket 6" itemId="0"/>
			<SocketIdURL nodeId="33989" name="Jewel 33989" itemPbURL=""/>
			<SocketIdURL nodeId="18436" name="Jewel 18436" itemPbURL=""/>
			<Slot itemPbURL="" name="Boots Abyssal Socket 3" itemId="0"/>
			<Slot itemPbURL="" name="Helmet Abyssal Socket 1" itemId="0"/>
			<Slot itemPbURL="" name="Belt Abyssal Socket 6" itemId="0"/>
			<Slot itemPbURL="" name="Weapon 2 Swap Abyssal Socket 5" itemId="0"/>
			<Slot itemPbURL="" name="Weapon 1 Abyssal Socket 1" itemId="0"/>
			<Slot itemPbURL="" name="Weapon 2 Abyssal Socket 1" itemId="0"/>
			<Slot itemPbURL="" name="Weapon 1 Abyssal Socket 4" itemId="0"/>
			<Slot itemPbURL="" name="Belt" itemId="9"/>
			<Slot itemPbURL="" name="Weapon 1 Swap Abyssal Socket 2" itemId="0"/>
			<Slot itemPbURL="" name="Weapon 1 Abyssal Socket 2" itemId="0"/>
			<Slot itemPbURL="" active="true" name="Flask 5" itemId="11"/>
			<Slot itemPbURL="" name="Boots Abyssal Socket 2" itemId="0"/>
			<Slot itemPbURL="" name="Belt Abyssal Socket 3" itemId="0"/>
			<Slot itemPbURL="" active="true" name="Flask 4" itemId="12"/>
			<Slot itemPbURL="" name="Gloves Abyssal Socket 1" itemId="0"/>
			<Slot itemPbURL="" name="Helmet Abyssal Socket 6" itemId="0"/>
			<Slot itemPbURL="" active="true" name="Flask 1" itemId="15"/>
			<SocketIdURL nodeId="61834" name="Jewel 61834" itemPbURL=""/>
			<Slot itemPbURL="" name="Gloves Abyssal Socket 5" itemId="0"/>
			<Slot itemPbURL="" name="Amulet" itemId="10"/>
			<Slot itemPbURL="" name="Weapon 1 Abyssal Socket 3" itemId="0"/>
			<Slot itemPbURL="" name="Weapon 2 Abyssal Socket 3" itemId="0"/>
			<Slot itemPbURL="" name="Gloves Abyssal Socket 4" itemId="0"/>
			<Slot itemPbURL="" active="true" name="Flask 2" itemId="13"/>
			<Slot itemPbURL="" name="Graft 1" itemId="0"/>
			<Slot itemPbURL="" name="Ring 2" itemId="6"/>
			<Slot itemPbURL="" name="Weapon 2 Swap" itemId="0"/>
			<Slot itemPbURL="" name="Gloves" itemId="8"/>
			<Slot itemPbURL="" name="Boots Abyssal Socket 5" itemId="0"/>
			<SocketIdURL nodeId="22748" name="Jewel 22748" itemPbURL=""/>
			<Slot itemPbURL="" active="true" name="Flask 3" itemId="14"/>
			<Slot itemPbURL="" name="Helmet Abyssal Socket 2" itemId="0"/>
			<Slot itemPbURL="" name="Helmet Abyssal Socket 3" itemId="0"/>
			<Slot itemPbURL="" name="Helmet Abyssal Socket 4" itemId="0"/>
			<Slot itemPbURL="" name="Boots Abyssal Socket 4" itemId="0"/>
			<SocketIdURL nodeId="60735" name="Jewel 60735" itemPbURL=""/>
			<Slot itemPbURL="" name="Weapon 1 Swap Abyssal Socket 3" itemId="0"/>
			<Slot itemPbURL="" name="Body Armour Abyssal Socket 1" itemId="0"/>
			<Slot itemPbURL="" name="Helmet Abyssal Socket 5" itemId="0"/>
			<Slot itemPbURL="" name="Weapon 1 Swap Abyssal Socket 1" itemId="0"/>
			<SocketIdURL nodeId="34483" name="Jewel 34483" itemPbURL=""/>
			<Slot itemPbURL="" name="Body Armour Abyssal Socket 2" itemId="0"/>
			<Slot itemPbURL="" name="Boots Abyssal Socket 6" itemId="0"/>
			<Slot itemPbURL="" name="Boots" itemId="1"/>
			<Slot itemPbURL="" name="Gloves Abyssal Socket 6" itemId="0"/>
			<Slot itemPbURL="" name="Gloves Abyssal Socket 3" itemId="0"/>
			<SocketIdURL nodeId="6910" name="Jewel 6910" itemPbURL=""/>
			<Slot itemPbURL="" name="Ring 1" itemId="5"/>
			<Slot itemPbURL="" name="Weapon 2 Abyssal Socket 4" itemId="0"/>
			<Slot itemPbURL="" name="Weapon 1 Swap Abyssal Socket 5" itemId="0"/>
			<Slot itemPbURL="" name="Body Armour Abyssal Socket 6" itemId="0"/>
			<Slot itemPbURL="" name="Gloves Abyssal Socket 2" itemId="0"/>
			<Slot itemPbURL="" name="Belt Abyssal Socket 4" itemId="0"/>
			<SocketIdURL nodeId="32763" name="Jewel 32763" itemPbURL=""/>
			<Slot itemPbURL="" name="Belt Abyssal Socket 1" itemId="0"/>
			<Slot itemPbURL="" name="Body Armour Abyssal Socket 3" itemId="0"/>
			<Slot itemPbURL="" name="Weapon 2 Swap Abyssal Socket 1" itemId="0"/>
			<Slot itemPbURL="" name="Helmet" itemId="4"/>
			<Slot itemPbURL="" name="Weapon 2 Swap Abyssal Socket 2" itemId="0"/>
			<Slot itemPbURL="" name="Boots Abyssal Socket 1" itemId="0"/>
			<Slot itemPbURL="" name="Weapon 2" itemId="2"/>
			<Slot itemPbURL="" name="Body Armour" itemId="3"/>
			<Slot itemPbURL="" name="Graft 2" itemId="0"/>
			<Slot itemPbURL="" name="Body Armour Abyssal Socket 4" itemId="0"/>
			<Slot itemPbURL="" name="Body Armour Abyssal Socket 5" itemId="0"/>
			<Slot itemPbURL="" name="Weapon 1 Swap" itemId="0"/>
			<SocketIdURL nodeId="33753" name="Jewel 33753" itemPbURL=""/>
			<Slot itemPbURL="" name="Belt Abyssal Socket 5" itemId="0"/>
			<Slot itemPbURL="" name="Weapon 2 Swap Abyssal Socket 3" itemId="0"/>
			<Slot itemPbURL="" name="Weapon 2 Abyssal Socket 2" itemId="0"/>
			<Slot itemPbURL="" name="Weapon 2 Swap Abyssal Socket 6" itemId="0"/>
			<Slot itemPbURL="" name="Weapon 2 Swap Abyssal Socket 4" itemId="0"/>
			<Slot itemPbURL="" name="Weapon 1 Swap Abyssal Socket 4" itemId="0"/>
		</ItemSet>
		<TradeSearchWeights/>
	</Items>
	<Config activeConfigSet="1">
		<ConfigSet title="Default" id="1">
			<Input name="bandit" string="Alira"/>
			<Input name="BrandsAttachedToEnemy" number="1"/>
			<Input name="useFrenzyCharges" boolean="true"/>
			<Input name="conditionEnemyChilled" boolean="true"/>
			<Input name="buffOnslaught" boolean="true"/>
			<Input name="multiplierNearbyRareOrUniqueEnemies" number="1"/>
			<Input name="conditionEnemyBleeding" boolean="true"/>
			<Input name="conditionBeenHitRecently" boolean="true"/>
			<Input name="pantheonMajorGod" string="Lunaris"/>
			<Input name="DisableEHPGainOnBlock" boolean="true"/>
			<Input name="projectileDistance" number="10"/>
			<Input name="conditionCritRecently" boolean="true"/>
			<Input name="multiplierNearbyEnemies" number="1"/>
			<Input name="conditionHaveTotem" boolean="true"/>
			<Input name="conditionGainedPowerChargeRecently" boolean="true"/>
			<Input name="usePowerCharges" boolean="true"/>
			<Input name="pantheonMinorGod" string="Ryslatha"/>
			<Input name="conditionEnemyIgnited" boolean="true"/>
			<Placeholder name="enemySpeed" number="700"/>
			<Placeholder name="enemyChaosResist" number="30"/>
			<Placeholder name="enemyLightningDamage" number="2241"/>
			<Placeholder name="enemyCritChance" number="5"/>
			<Placeholder name="ShockStacks" number="1"/>
			<Placeholder name="enemyColdDamage" number="2241"/>
			<Placeholder name="enemyFireDamage" number="2241"/>
			<Placeholder name="enemyLevel" number="84"/>
			<Placeholder name="multiplierWitheredStackCountSelf" number="15"/>
			<Placeholder name="enemyColdResist" number="50"/>
			<Placeholder name="enemyLightningPen" number="3"/>
			<Placeholder name="enemyLightningResist" number="50"/>
			<Placeholder name="enemyEvasion" number="10143"/>
			<Placeholder name="multiplierEnemyHallowingFlame" number="1"/>
			<Placeholder name="meleeDistance" number="15"/>
			<Placeholder name="enemyCritDamage" number="30"/>
			<Placeholder name="enemyColdPen" number="3"/>
			<Placeholder name="enemyChaosDamage" number="896"/>
			<Placeholder name="projectileDistance" number="40"/>
			<Placeholder name="enemyFireResist" number="50"/>
			<Placeholder name="multiplierHallowingFlameStacksRemovedByAlly" number="1"/>
			<Placeholder name="ScorchStacks" number="1"/>
			<Placeholder name="enemyDamageRollRange" number="70"/>
			<Placeholder name="enemyArmour" number="61989"/>
			<Placeholder name="sigilOfPowerStages" number="1"/>
			<Placeholder name="configSpectralTigerCount" number="5"/>
			<Placeholder name="enemyFirePen" number="3"/>
			<Placeholder name="enemyPhysicalDamage" number="2241"/>
		</ConfigSet>
	</Config>
</PathOfBuilding>
