{
  "skill": "Armageddon Brand of Recall",
  "normalized_name": "armageddon_brand_of_recall",
  "source_url": "https://pobb.in/GTkqCnjXghWY",
  "source_type": "pobb_in",
  "region": "en",
  "pob_url": "https://pobb.in/GTkqCnjXghWY",
  "xml_path": "C:\\Users\\saulo\\Documents\\Agente - PoE\\data\\poe_ninja\\poe_ninja_dataset\\xml\\armageddon_brand_of_recall\\GTkqCnjXghWY.xml",
  "patch": "3_0",
  "league": "ancestors",
  "author": "",
  "build_title": "",
  "collected_at": "2026-07-12T18:40:38Z",
  "status": "needs_review",
  "class": "Witch",
  "ascendancy": "Elementalist"
}