{
  "skill": "Bladefall of Volleys",
  "normalized_name": "bladefall_of_volleys",
  "source": "poe.ninja api",
  "source_url": "https://poe.ninja/poe1/api/builds/0708-20260717-49664/search?overview=mirage&type=exp&skills=Bladefall+of+Volleys",
  "endpoint": "https://poe.ninja/poe1/api/builds/0708-20260717-49664/character?account=rozey2-3646&name=Mirage_Roozey&overview=mirage&type=0&timeMachine=",
  "account": "rozey2-3646",
  "character": "Mirage_Roozey",
  "league": "mirage",
  "version": "0708-20260717-49664",
  "snapshot": "mirage",
  "class": "Gladiator",
  "ascendancy": "Gladiator",
  "level": 100,
  "xml_path": "C:\\Users\\joao.carvalho\\Desktop\\Robô\\Agente - PoE_GDRIVE_STAGE\\data\\poe_ninja\\poe_ninja_dataset\\xml\\bladefall_of_volleys\\rozey2_3646_mirage_roozey.xml",
  "collected_at": "2026-07-17T07:57:51Z",
  "status": "generated"
}