{
  "skill": "Rallying Cry",
  "normalized_name": "rallying_cry",
  "source": "poe.ninja api",
  "source_url": "https://poe.ninja/poe1/api/builds/0653-20260721-53013/search?overview=standard&type=exp&skills=Rallying+Cry",
  "endpoint": "https://poe.ninja/poe1/api/builds/0653-20260721-53013/character?account=Dangse12-3204&name=dangseduel&overview=standard&type=0&timeMachine=",
  "account": "Dangse12-3204",
  "character": "dangseduel",
  "league": "mirage",
  "version": "0653-20260721-53013",
  "snapshot": "standard",
  "class": "Slayer",
  "ascendancy": "Slayer",
  "level": 95,
  "xml_path": "C:\\Users\\joao.carvalho\\Desktop\\Robô\\Agente - PoE_GDRIVE_STAGE\\data\\poe_ninja\\poe_ninja_dataset\\xml\\rallying_cry\\dangse12_3204_dangseduel.xml",
  "collected_at": "2026-07-21T08:35:12Z",
  "status": "generated"
}