{
  "skill": "Ancestral Cry",
  "normalized_name": "ancestral_cry",
  "source": "poe.ninja api",
  "source_url": "https://poe.ninja/poe1/api/builds/2024.11.0/search?overview=ancestors&type=exp&skills=Ancestral+Cry",
  "endpoint": "https://poe.ninja/poe1/api/builds/2024.11.0/character?account=Dinoblin-7756&name=Gubadin&overview=ancestors&type=exp&timeMachine=",
  "account": "Dinoblin-7756",
  "character": "Gubadin",
  "league": "ancestors",
  "version": "2024.11.0",
  "class": "Paladin",
  "ascendancy": null,
  "level": 94,
  "xml_path": "C:\\Users\\saulo\\Documents\\Agente - PoE\\data\\poe_ninja\\poe_ninja_dataset\\xml\\ancestral_cry\\dinoblin_7756_gubadin.xml",
  "collected_at": "2026-07-13T08:38:12Z",
  "status": "generated"
}