{
  "skill": "List of Vaal skill gems",
  "normalized_name": "list_of_vaal_skill_gems",
  "source": "poe.ninja api",
  "source_url": "https://poe.ninja/poe1/api/builds/1212-20260720-03796/search?overview=mirage&type=exp&skills=List+of+Vaal+skill+gems",
  "endpoint": "https://poe.ninja/poe1/api/builds/1212-20260720-03796/character?account=Poteitik-3151&name=GarfSkinEnjoyerrr&overview=mirage&type=0&timeMachine=",
  "account": "Poteitik-3151",
  "character": "GarfSkinEnjoyerrr",
  "league": "mirage",
  "version": "1212-20260720-03796",
  "snapshot": "mirage",
  "class": "Pathfinder",
  "ascendancy": "Pathfinder",
  "level": 100,
  "xml_path": "C:\\Users\\joao.carvalho\\Desktop\\Robô\\Agente - PoE_GDRIVE_STAGE\\data\\poe_ninja\\poe_ninja_dataset\\xml\\list_of_vaal_skill_gems\\poteitik_3151_garfskinenjoyerrr.xml",
  "collected_at": "2026-07-20T13:29:45Z",
  "status": "generated"
}